metricq_tools/__init__.py
metricq_tools/check.py
metricq_tools/csv.py
metricq_tools/discover.py
metricq_tools/energy.py
metricq_tools/inspect.py
metricq_tools/logging.py
metricq_tools/send.py
metricq_tools/slurm.py
metricq_tools/spy.py
metricq_tools/summary.py
metricq_tools/utils.py
metricq_tools/version.py
metricq_tools-1.0.0.dist-info/LICENSE
metricq_tools-1.0.0.dist-info/METADATA
metricq_tools-1.0.0.dist-info/WHEEL
metricq_tools-1.0.0.dist-info/entry_points.txt
metricq_tools-1.0.0.dist-info/top_level.txt
metricq_tools-1.0.0.dist-info/RECORD
