Metadata-Version: 2.1
Name: metricq-tools
Version: 1.0.0
Summary: Useful scripts to manage and inspect a MetricQ instance
Home-page: https://github.com/metricq/metricq-tools
Author: TU Dresden
License: GPL3
Classifier: License :: OSI Approved :: GNU General Public License v3 or later (GPLv3+)
Classifier: Programming Language :: Python :: 3
Requires-Python: >=3.10
License-File: LICENSE
Requires-Dist: metricq (~=5.1)
Requires-Dist: click
Requires-Dist: click-log
Requires-Dist: async-timeout (~=3.0)
Requires-Dist: humanize (~=2.5)
Requires-Dist: python-dateutil (~=2.8)
Requires-Dist: python-dotenv (~=1.0.0)
Requires-Dist: python-hostlist
Requires-Dist: numpy
Requires-Dist: termplotlib
Requires-Dist: tabulate
Provides-Extra: dev
Requires-Dist: pytest ; extra == 'dev'
Requires-Dist: black (==22.10.0) ; extra == 'dev'
Requires-Dist: flake8 ; extra == 'dev'
Requires-Dist: isort (~=5.0) ; extra == 'dev'
Requires-Dist: check-manifest ; extra == 'dev'
Requires-Dist: pre-commit ; extra == 'dev'
Requires-Dist: mypy (>=1.2.0) ; extra == 'dev'
Requires-Dist: types-tabulate ; extra == 'dev'
Requires-Dist: types-python-dateutil ; extra == 'dev'
Requires-Dist: tox ; extra == 'dev'
Provides-Extra: lint
Requires-Dist: black (==22.10.0) ; extra == 'lint'
Requires-Dist: flake8 ; extra == 'lint'
Requires-Dist: isort (~=5.0) ; extra == 'lint'
Requires-Dist: check-manifest ; extra == 'lint'
Requires-Dist: pre-commit ; extra == 'lint'
Provides-Extra: test
Requires-Dist: pytest ; extra == 'test'
Provides-Extra: typing
Requires-Dist: mypy (>=1.2.0) ; extra == 'typing'
Requires-Dist: types-tabulate ; extra == 'typing'
Requires-Dist: types-python-dateutil ; extra == 'typing'
Requires-Dist: pytest ; extra == 'typing'
